wu_diff/__init__.py
wu_diff/wu_diff.py
wu_diff-0.1.1.dist-info/WHEEL
wu_diff-0.1.1.dist-info/METADATA
wu_diff-0.1.1.dist-info/RECORD
